{
  "status": "done",
  "assets": {
    "CGIMailForm-bundle.js": {
      "name": "CGIMailForm-bundle.js",
      "path": "/app/base/static/bundles/CGIMailForm-bundle.js"
    },
    "CGIMailForm-bundle.js.LICENSE.txt": {
      "name": "CGIMailForm-bundle.js.LICENSE.txt",
      "path": "/app/base/static/bundles/CGIMailForm-bundle.js.LICENSE.txt"
    },
    "main-bundle.js": {
      "name": "main-bundle.js",
      "path": "/app/base/static/bundles/main-bundle.js"
    },
    "main-bundle.js.LICENSE.txt": {
      "name": "main-bundle.js.LICENSE.txt",
      "path": "/app/base/static/bundles/main-bundle.js.LICENSE.txt"
    },
    "NewsFeed-bundle.js": {
      "name": "NewsFeed-bundle.js",
      "path": "/app/base/static/bundles/NewsFeed-bundle.js"
    },
    "NewsFeed-bundle.js.LICENSE.txt": {
      "name": "NewsFeed-bundle.js.LICENSE.txt",
      "path": "/app/base/static/bundles/NewsFeed-bundle.js.LICENSE.txt"
    }
  },
  "chunks": {
    "CGIMailForm": [
      "CGIMailForm-bundle.js"
    ],
    "main": [
      "main-bundle.js"
    ],
    "NewsFeed": [
      "NewsFeed-bundle.js"
    ]
  }
}